athlinks_races/__init__.py
athlinks_races/app.py
athlinks_races/cli.py
athlinks_races/demo.py
athlinks_races/items.py
athlinks_races/pipelines.py
athlinks_races/settings.py
athlinks_races/spiders/__init__.py
athlinks_races/spiders/race.py
athlinks_races-0.0.5.dist-info/LICENSE
athlinks_races-0.0.5.dist-info/METADATA
athlinks_races-0.0.5.dist-info/WHEEL
athlinks_races-0.0.5.dist-info/entry_points.txt
athlinks_races-0.0.5.dist-info/top_level.txt
athlinks_races-0.0.5.dist-info/RECORD
