Metadata-Version: 2.2
Name: athlinks-races
Version: 0.0.5
Summary: Web scraper for race results hosted on Athlinks.
Author-email: Jose Vicente Nunez <kodegeek.com@protonmail.com>, Aaron Schroeder <aaron@trailzealot.com>
License: MIT License
Project-URL: Homepage, https://kodegeek.com/
Project-URL: Repository, https://github.com/josevnz/athlinks-races/
Keywords: running,race,tower race,racing
Classifier: Environment :: Console
Classifier: Development Status :: 3 - Alpha
Classifier: License :: OSI Approved :: MIT License
Classifier: Intended Audience :: Developers
Classifier: Programming Language :: Python :: 3
Requires-Python: >=3.11
License-File: LICENSE
Requires-Dist: Scrapy==2.11.2
Requires-Dist: textual==1.0.0
Provides-Extra: lint
Requires-Dist: pylint; extra == "lint"
Provides-Extra: dev
Requires-Dist: twine; extra == "dev"
Requires-Dist: pytest; extra == "dev"
Requires-Dist: textual-dev; extra == "dev"
Requires-Dist: docutils-stubs==0.0.22; extra == "dev"
